flowly/__init__.py
flowly/core/__init__.py
flowly/core/main.py
flowly-0.0.1.dist-info/METADATA
flowly-0.0.1.dist-info/WHEEL
flowly-0.0.1.dist-info/licenses/LICENSE
flowly-0.0.1.dist-info/RECORD
