Metadata-Version: 2.3
Name: flowly
Version: 0.0.1
Summary: A package for dataflow programming with Python.
Project-URL: Homepage, https://github.com/j8sr0230/flowly
Project-URL: Bug Tracker, https://github.com/j8sr0230/flowly/issues
Author-email: Ronny Scharf-Wildenhain <ronny.scharf08@gmail.com>
License-File: LICENSE
Classifier: License :: OSI Approved :: GNU Lesser General Public License v2 or later (LGPLv2+)
Classifier: Operating System :: OS Independent
Classifier: Programming Language :: Python :: 3
Requires-Python: >=3.12
